CHANGELOG
MANIFEST.in
README.rst
setup.py
RealThreading.egg-info/PKG-INFO
RealThreading.egg-info/SOURCES.txt
RealThreading.egg-info/dependency_links.txt
RealThreading.egg-info/requires.txt
RealThreading.egg-info/top_level.txt
rt/__init__.py
rt/_launcher.py
rt/lock.py
rt/thread.py