Metadata-Version: 1.1
Name: RealThreading
Version: 0.0.1
Summary: 'A python's parallel processing module.
Home-page: UNKNOWN
Author: G.M
Author-email: G.Mpydev@gmail.com
License: MIT
Keywords: threading,processing,parallel,multi-processing
Platform: win32
Classifier: Development Status :: 3 - Alpha
Classifier: Intended Audience :: Developers
Classifier: Intended Audience :: Information Technology
Classifier: Natural Language :: English
Classifier: Operating System :: Microsoft :: Windows
Classifier: Programming Language :: Python :: 3.5
Classifier: Topic :: Software Development :: Build Tools
Classifier: Topic :: Software Development :: Libraries :: Python Modules
Classifier: Topic :: Software Development :: Libraries :: Python Modules
Classifier: Topic :: System :: Hardware :: Symmetric Multi-processing
